mem.sv
`timescale 1ns/1ns

module mem(
    input  logic clk,
    input  logic rd,
    input  logic wr,
    input  logic [`ADDR_LEN-1:0] addr,
    input  logic [`DATA_LEN-1:0] data_in,
    output logic [`DATA_LEN-1:0] data_out
);

logic [`DATA_LEN-1:0] data [0:`ADDRS-1];

always @(posedge clk) begin
    if (wr)
        data[addr] <= data_in;
    if (rd)
        data_out <= data[addr];
end


endmodule

sigmoid.sv
`timescale 1ns/1ns

module sigmoid(
    input  logic [`OP_SIZE-1:0] x,
    output logic [`OP_SIZE-1:0] y
);

localparam MT4 = `OP_SIZE-14;
localparam DOUBLE_SIZE = (`OP_SIZE)*2;
localparam SINGLE_SIZE = `OP_SIZE;
localparam HALF_SIZE = (`OP_SIZE)>>1;
localparam HALF = {{HALF_SIZE{1'b0}},1'b1,{(HALF_SIZE-1){1'b0}}};
localparam HALF_NEG = {{HALF_SIZE{1'b1}},1'b0,{(HALF_SIZE-1){1'b1}}};

logic neg, more_then_4;
assign neg = x[`OP_SIZE-1];
assign more_then_4 = neg ? !(&x[`OP_SIZE-1:MT4])
                         :   |x[`OP_SIZE-1:MT4];

logic [DOUBLE_SIZE-1:0] z, x_signed;
logic [SINGLE_SIZE-1:0] x_func;
assign x_signed = {{SINGLE_SIZE{neg}}, x};
assign x_func = SINGLE_SIZE'({{2{neg}},x_signed[DOUBLE_SIZE-1:2]}) + 
                    (neg ? SINGLE_SIZE'(1<<HALF_SIZE) : {{HALF_SIZE{1'b1}},{HALF_SIZE{1'b0}}});
assign z = { {SINGLE_SIZE{1'(!neg)}} ,SINGLE_SIZE'(x_func)};

logic [DOUBLE_SIZE-1:0] z_sqr, z_shift;
assign z_sqr = z*z;
assign z_shift = z_sqr>>(HALF_SIZE+1);

assign y = more_then_4 ? neg ? HALF_NEG : HALF
                       : neg ? SINGLE_SIZE'(z_shift)+HALF_NEG
                             : SINGLE_SIZE'(HALF<<1)-SINGLE_SIZE'(z_shift)+HALF_NEG;

endmodule

pe.sv
`timescale 1ns/1ns

module pe(
    input logic clk,
    input logic rst,
    input logic op,
    input logic e,
    input logic [`OP_SIZE-1:0] op1,
    input logic [`OP_SIZE-1:0] op2,
    output logic [`OP_SIZE-1:0] res
);

`define FLOAT_PART 16

localparam DOUBLE_SIZE = (`OP_SIZE)*2;
localparam SINGLE_SIZE = `OP_SIZE;

logic e_ff;
logic [DOUBLE_SIZE-1:0] op1_ff, op2_ff, res_ff;
logic [`OP_SIZE-1:0] sigm, x;

assign x = SINGLE_SIZE'(op1_ff + op2_ff);

assign res_ff = e_ff ? 0
                     : op ? op1_ff * op2_ff
                          : e ? DOUBLE_SIZE'(sigm)
                              : op1_ff + op2_ff;

assign res = op ? res_ff[`FLOAT_PART+`OP_SIZE-1:`FLOAT_PART]
                : res_ff[`OP_SIZE-1:0];

always @(posedge clk, negedge rst) begin
    if (rst) begin
        op1_ff <= 0;
        op2_ff <= 0;
    end else if (e | e_ff) begin
        op1_ff <= 0;
        op2_ff <= 0;
    end else begin
        op1_ff <= {{SINGLE_SIZE{op1[`OP_SIZE-1]}},op1};
        op2_ff <= {{SINGLE_SIZE{op2[`OP_SIZE-1]}},op2};
    end
end

always @(posedge clk, negedge rst) begin
    if(rst)
        e_ff<=0;
    else
        e_ff<=e;
end



sigmoid sigmoid_i(
    .x(x),
    .y(sigm)
);

endmodule

storage_stack.sv
`timescale 1ns/1ns

module storage_stack(
    input logic clk,
    input logic push,
    input logic pop,
    input logic [`OP_SIZE-1:0] data_in,
    output logic [`OP_SIZE-1:0] data_out
);

`define STACK_DEPTH 1024
`define STACK_ADDR_SIZE 10

logic [`OP_SIZE-1:0] data      [0:`STACK_DEPTH-1];
logic [`OP_SIZE-1:0] data_next [0:`STACK_DEPTH-1];

assign data_out = data[0];

assign data_next[0] = push ? data_in
                           : pop ? data[1]
                                 : data[0];

always @(posedge clk)
    data[0] <= data_next[0];

assign data_next[`STACK_DEPTH-1] = push ? data[{`STACK_ADDR_SIZE{1'b1}}]
                                        : pop ? '0
                                              : data[`STACK_DEPTH-1];

always @(posedge clk)
    data[`STACK_DEPTH-1] <= data_next[`STACK_DEPTH-1];

generate 
    for (genvar idx = 1; idx < (`STACK_DEPTH-1); idx++) begin
        assign data_next[idx] = push ? data[idx-1]
                                     : pop ? data[idx+1]
                                           : data[idx];

        always @(posedge clk)
            data[idx] <= data_next[idx];
    end
endgenerate

endmodule

storage_queue.sv
`timescale 1ns/1ns

module storage_queue(
    input logic clk,
    input logic rst,
    input logic push,
    input logic pop,
    input logic reset,
    input logic next,
    input logic [`OP_SIZE-1:0] data_in,
    output logic [`OP_SIZE-1:0] data_out,
    output logic empty
);

`define QUEUE_DEPTH 64
`define QUEUE_ADDR_SIZE 6

logic [`OP_SIZE-1:0] data [0:`QUEUE_DEPTH-1];
logic [`QUEUE_ADDR_SIZE-1:0] addr_start, addr_end, addr_end_tmp;
logic [`QUEUE_ADDR_SIZE-1:0] addr_start_next, addr_end_next, addr_end_tmp_next;

assign data_out = data[addr_end];
assign addr_start_next   = push ? addr_start + 1 : addr_start;
assign addr_end_next     = reset ? addr_end_tmp
                                 : pop  
                                    ? addr_end + 1 
                                    : addr_end;

assign addr_end_tmp_next = next ? addr_end
                                : addr_end_tmp;

assign empty = addr_start <= addr_end_tmp + 3;

always @(posedge clk, negedge rst) begin
    if (rst) begin
        addr_start <= '0;
        addr_end <= '0;
        addr_end_tmp <= '0;
    end else begin 
        addr_start <= addr_start_next;
        addr_end   <= addr_end_next;
        addr_end_tmp <= addr_end_tmp_next;
    end
end

always @(posedge clk) begin
    if(push)
        data[addr_start] <= data_in;
end

endmodule

exec_top.sv
`timescale 1ns/1ns

module exec_top(
    input logic clk,
    input logic rst,
    input logic r,
    input logic e,
    input logic o1,
    input logic o2,
    input logic w1,
    input logic w2,
    input logic reset,
    input logic next,
    input logic [`OP_SIZE-1:0] op,
    output logic computation_end
);

logic push_o1, push_o2, push_w1, push_w2;
logic pop_o1, pop_o2, pop_w1, pop_w2;
logic emp_1, emp_2;
logic reset_o1, reset_o2, next_o1, next_o2;

logic [`OP_SIZE-1:0] data_out_o1, data_out_o2,
                     data_out_w1, data_out_w2;

logic [`OP_SIZE-1:0] data_out_m1, data_out_m2;
logic [`OP_SIZE-1:0] data_out_s1, data_out_s2;

logic [`OP_SIZE-1:0] data_out_s2_e;

logic [`OP_SIZE-1:0] operand;

assign data_out_s2_e = e ? 0 : data_out_s2;

assign push_o1 = !r & !next & !reset & o1;
assign push_o2 = !r & !next & !reset & o2;
assign push_w1 = !r & !next & !reset & w1;
assign push_w2 = !r & !next & !reset & w2;

assign pop_o1 = r & o1;
assign pop_o2 = r & o2;
assign pop_w1 = r & w1;
assign pop_w2 = r & w2;

assign reset_o1 = reset & o1;
assign reset_o2 = reset & o2;

assign next_o1 = next & o1;
assign next_o2 = next & o2;

assign operand = (e & (o1 | o2 | w1 | w2)) ? data_out_s2 : op;

storage_queue storage_queue_i1(
    .clk (clk),
    .rst (rst),
    .push (push_o1),
    .pop (pop_o1),
    .reset (reset_o1),
    .next (next_o1),
    .data_in (operand),
    .data_out(data_out_o1),
    .empty (emp_1)
);

`ifdef TWO_LAY

storage_queue storage_queue_i2(
    .clk (clk),
    .rst (rst),
    .push (push_o2),
    .pop (pop_o2),
    .reset (reset_o2),
    .next (next_o2),
    .data_in (operand),
    .data_out(data_out_o2),
    .empty (emp_2)
);

assign computation_end = emp_1 & emp_2;

`ifdef DISPLAY_ANSWER

real answer;
always @(posedge clk) begin
    answer = data_out_o1[`OP_SIZE-1:0] + {{16{1'b0}},1'b1, {14{1'b0}},1'b1};
    if (computation_end & data_out_o1!=0) begin
        $display("%f",answer/(2**16));
    end
end

`endif

`endif
`ifndef TWO_LAY

assign data_out_o2 = 0;
assign computation_end = emp_1;

`endif

storage_stack storage_stack_i1(
    .clk (clk),
    .push (push_w1),
    .pop (pop_w1),
    .data_in (operand),
    .data_out(data_out_w1)
);

storage_stack storage_stack_i2(
    .clk (clk),
    .push (push_w2),
    .pop (pop_w2),
    .data_in (operand),
    .data_out(data_out_w2)
);

pe module_pe_mul1(
    .clk (clk),
    .rst (rst),
    .op  (1),
    .e   (e),
    .op1 (data_out_o1),
    .op2 (data_out_w1),
    .res (data_out_m1)
);

pe module_pe_mul2(
    .clk (clk),
    .rst (rst),
    .op  (1),
    .e   (e),
    .op1 (data_out_o2),
    .op2 (data_out_w2),
    .res (data_out_m2)
);

pe module_pe_sum1(
    .clk (clk),
    .rst (rst),
    .op  (0),
    .e   (e),
    .op1 (data_out_m1),
    .op2 (data_out_m2),
    .res (data_out_s1)
);

pe module_pe_sum2(
    .clk (clk),
    .rst (rst),
    .op  (0),
    .e   (e),
    .op1 (data_out_s1),
    .op2 (data_out_s2_e),
    .res (data_out_s2)
);

endmodule

fetch.sv
`timescale 1ns/1ns

module fetch(
    input logic clk,
    input logic rst,
    // mem
    input logic rd,
    input  logic [`DATA_LEN-1:0] data_in,
    output logic computation_end
);

`ifndef OP_SIZE
`define OP_SIZE `DATA_LEN-8
`endif

logic r,e,o1,o2,w1,w2,reset,next;
logic [`OP_SIZE-1:0] op;

assign r  = data_in[`DATA_LEN-1];
assign e  = data_in[`DATA_LEN-2];
assign o1 = data_in[`DATA_LEN-3];
assign o2 = data_in[`DATA_LEN-4];
assign w1 = data_in[`DATA_LEN-5];
assign w2 = data_in[`DATA_LEN-6];
assign reset = data_in[`DATA_LEN-7];
assign next  = data_in[`DATA_LEN-8];
assign op = data_in[`OP_SIZE-1:0];

logic [31:0] counter;

always @(posedge clk)
	counter <= counter+1;

exec_top exec_top_i(
    .clk (clk),
    .rst (rst),
    .r (r),
    .e (e),
    .o1 (o1),
    .o2 (o2),
    .w1 (w1),
    .w2 (w2),
    .reset (reset),
    .next (next),
    .op (op),
    .computation_end (computation_end)
);

endmodule

our.sv
`timescale 1ns/1ns
  module our;
logic clk;
logic rst;

`define DISPLAY_ANSWER
`define TWO_LAY
`define ADDR_LEN 11
`define ADDRS 2048
`define DATA_LEN 40

localparam CHAR_PART = `DATA_LEN/8;

initial begin
	clk= 0;
	forever begin
    		#5 clk = ~clk; 
	end
end

initial begin
	rst = 1;
	#10;
	rst = 0; 
end

logic rd;
logic wr;
logic [`ADDR_LEN-1:0] addr;
logic [`DATA_LEN-1:0] data_in;
logic [`DATA_LEN-1:0] data_out;
logic computation_end;

fetch fetch_i(
	.clk (clk),
	.rst (rst),

	.rd (rd),
	.data_in (data_out),
	.computation_end (computation_end)
	);
mem mem_i(
	.clk (clk),
	.rd (rd),
	.wr (wr),
	.addr (addr),
	.data_in (data_in),
	.data_out (data_out)
);

integer file_handle;
logic [8-1:0] file_char;
logic [`DATA_LEN-1:0] file_data;
integer counter;

initial begin
	$dumpfile("test.vcd");
	$dumpvars();

// `ifndef TWO_LAY
	file_handle = $fopen("dump", "r");
// `endif
// `ifdef TWO_LAY
// 	file_handle = $fopen("dump2", "r");
// `endif

	@(posedge clk);

	addr = '0;
	wr = 0;
	rd = 0;
	counter = 0;
	while (!$feof(file_handle)) begin
		file_data = '0;
		for(int i=0; i<CHAR_PART; i++) begin
			file_char = $fgetc(file_handle);
			file_data = (file_data<<8) | `DATA_LEN'(file_char);
		end
		counter++;
		wr = 1;
		data_in = file_data;
		@(posedge clk);
		addr = addr + 1;
	end
	addr = '0;
	wr = 0;
	rd = 1;
	repeat(counter) begin
		@(posedge clk);
		addr = addr + 1;
	end

	for(int i=0; i<50; i++) begin
		@(posedge clk);
		if (computation_end) break;
	end
	$fclose(file_handle);
	$finish;
end
  endmodule

test.vcd
$version Generated by VerilatedVcd $end
$timescale 1ns $end
 $scope module TOP $end
  $scope module our $end
   $var wire 1 M! clk $end
   $var wire 1 N! rst $end
   $var wire 32 V! CHAR_PART [31:0] $end
   $var wire 1 # rd $end
   $var wire 1 $ wr $end
   $var wire 11 % addr [10:0] $end
   $var wire 40 & data_in [39:0] $end
   $var wire 40 .! data_out [39:0] $end
   $var wire 1 / computation_end $end
   $var wire 32 ( file_handle [31:0] $end
   $var wire 8 ) file_char [7:0] $end
   $var wire 40 * file_data [39:0] $end
   $var wire 32 , counter [31:0] $end
   $scope module fetch_i $end
    $var wire 1 M! clk $end
    $var wire 1 N! rst $end
    $var wire 1 # rd $end
    $var wire 40 .! data_in [39:0] $end
    $var wire 1 / computation_end $end
    $var wire 1 0! r $end
    $var wire 1 1! e $end
    $var wire 1 2! o1 $end
    $var wire 1 3! o2 $end
    $var wire 1 4! w1 $end
    $var wire 1 5! w2 $end
    $var wire 1 6! reset $end
    $var wire 1 7! next $end
    $var wire 32 8! op [31:0] $end
    $var wire 32 O! counter [31:0] $end
    $scope module exec_top_i $end
     $var wire 1 M! clk $end
     $var wire 1 N! rst $end
     $var wire 1 0! r $end
     $var wire 1 1! e $end
     $var wire 1 2! o1 $end
     $var wire 1 3! o2 $end
     $var wire 1 4! w1 $end
     $var wire 1 5! w2 $end
     $var wire 1 6! reset $end
     $var wire 1 7! next $end
     $var wire 32 8! op [31:0] $end
     $var wire 1 / computation_end $end
     $var wire 1 9! push_o1 $end
     $var wire 1 :! push_o2 $end
     $var wire 1 ;! push_w1 $end
     $var wire 1 <! push_w2 $end
     $var wire 1 =! pop_o1 $end
     $var wire 1 >! pop_o2 $end
     $var wire 1 ?! pop_w1 $end
     $var wire 1 @! pop_w2 $end
     $var wire 1 0 emp_1 $end
     $var wire 1 1 emp_2 $end
     $var wire 1 A! reset_o1 $end
     $var wire 1 B! reset_o2 $end
     $var wire 1 C! next_o1 $end
     $var wire 1 D! next_o2 $end
     $var wire 32 G! data_out_o1 [31:0] $end
     $var wire 32 H! data_out_o2 [31:0] $end
     $var wire 32 E! data_out_w1 [31:0] $end
     $var wire 32 F! data_out_w2 [31:0] $end
     $var wire 32 2 data_out_m1 [31:0] $end
     $var wire 32 3 data_out_m2 [31:0] $end
     $var wire 32 I! data_out_s1 [31:0] $end
     $var wire 32 J! data_out_s2 [31:0] $end
     $var wire 32 K! data_out_s2_e [31:0] $end
     $var wire 32 L! operand [31:0] $end
     $var real 64 P! answer $end
     $scope module storage_stack_i1 $end
      $var wire 1 M! clk $end
      $var wire 1 ;! push $end
      $var wire 1 ?! pop $end
      $var wire 32 L! data_in [31:0] $end
      $var wire 32 E! data_out [31:0] $end
     $upscope $end
     $scope module storage_stack_i2 $end
      $var wire 1 M! clk $end
      $var wire 1 <! push $end
      $var wire 1 @! pop $end
      $var wire 32 L! data_in [31:0] $end
      $var wire 32 F! data_out [31:0] $end
     $upscope $end
     $scope module module_pe_mul1 $end
      $var wire 1 M! clk $end
      $var wire 1 N! rst $end
      $var wire 1 W! op $end
      $var wire 1 1! e $end
      $var wire 32 G! op1 [31:0] $end
      $var wire 32 E! op2 [31:0] $end
      $var wire 32 2 res [31:0] $end
      $var wire 32 X! DOUBLE_SIZE [31:0] $end
      $var wire 32 Y! SINGLE_SIZE [31:0] $end
      $var wire 1 4 e_ff $end
      $var wire 64 5 op1_ff [63:0] $end
      $var wire 64 7 op2_ff [63:0] $end
      $var wire 64 9 res_ff [63:0] $end
      $var wire 32 ; sigm [31:0] $end
      $var wire 32 < x [31:0] $end
      $scope module sigmoid_i $end
       $var wire 32 < x [31:0] $end
       $var wire 32 ; y [31:0] $end
       $var wire 32 Z! MT4 [31:0] $end
       $var wire 32 X! DOUBLE_SIZE [31:0] $end
       $var wire 32 Y! SINGLE_SIZE [31:0] $end
       $var wire 32 [! HALF_SIZE [31:0] $end
       $var wire 32 \! HALF [31:0] $end
       $var wire 32 ]! HALF_NEG [31:0] $end
       $var wire 1 = neg $end
       $var wire 1 > more_then_4 $end
       $var wire 64 ? z [63:0] $end
       $var wire 64 A x_signed [63:0] $end
       $var wire 32 C x_func [31:0] $end
       $var wire 64 D z_sqr [63:0] $end
       $var wire 64 F z_shift [63:0] $end
      $upscope $end
     $upscope $end
     $scope module module_pe_mul2 $end
      $var wire 1 M! clk $end
      $var wire 1 N! rst $end
      $var wire 1 W! op $end
      $var wire 1 1! e $end
      $var wire 32 H! op1 [31:0] $end
      $var wire 32 F! op2 [31:0] $end
      $var wire 32 3 res [31:0] $end
      $var wire 32 X! DOUBLE_SIZE [31:0] $end
      $var wire 32 Y! SINGLE_SIZE [31:0] $end
      $var wire 1 H e_ff $end
      $var wire 64 I op1_ff [63:0] $end
      $var wire 64 K op2_ff [63:0] $end
      $var wire 64 M res_ff [63:0] $end
      $var wire 32 O sigm [31:0] $end
      $var wire 32 P x [31:0] $end
      $scope module sigmoid_i $end
       $var wire 32 P x [31:0] $end
       $var wire 32 O y [31:0] $end
       $var wire 32 Z! MT4 [31:0] $end
       $var wire 32 X! DOUBLE_SIZE [31:0] $end
       $var wire 32 Y! SINGLE_SIZE [31:0] $end
       $var wire 32 [! HALF_SIZE [31:0] $end
       $var wire 32 \! HALF [31:0] $end
       $var wire 32 ]! HALF_NEG [31:0] $end
       $var wire 1 Q neg $end
       $var wire 1 R more_then_4 $end
       $var wire 64 S z [63:0] $end
       $var wire 64 U x_signed [63:0] $end
       $var wire 32 W x_func [31:0] $end
       $var wire 64 X z_sqr [63:0] $end
       $var wire 64 Z z_shift [63:0] $end
      $upscope $end
     $upscope $end
     $scope module module_pe_sum1 $end
      $var wire 1 M! clk $end
      $var wire 1 N! rst $end
      $var wire 1 ^! op $end
      $var wire 1 1! e $end
      $var wire 32 2 op1 [31:0] $end
      $var wire 32 3 op2 [31:0] $end
      $var wire 32 I! res [31:0] $end
      $var wire 32 X! DOUBLE_SIZE [31:0] $end
      $var wire 32 Y! SINGLE_SIZE [31:0] $end
      $var wire 1 \ e_ff $end
      $var wire 64 ] op1_ff [63:0] $end
      $var wire 64 _ op2_ff [63:0] $end
      $var wire 64 R! res_ff [63:0] $end
      $var wire 32 a sigm [31:0] $end
      $var wire 32 b x [31:0] $end
      $scope module sigmoid_i $end
       $var wire 32 b x [31:0] $end
       $var wire 32 a y [31:0] $end
       $var wire 32 Z! MT4 [31:0] $end
       $var wire 32 X! DOUBLE_SIZE [31:0] $end
       $var wire 32 Y! SINGLE_SIZE [31:0] $end
       $var wire 32 [! HALF_SIZE [31:0] $end
       $var wire 32 \! HALF [31:0] $end
       $var wire 32 ]! HALF_NEG [31:0] $end
       $var wire 1 c neg $end
       $var wire 1 d more_then_4 $end
       $var wire 64 e z [63:0] $end
       $var wire 64 g x_signed [63:0] $end
       $var wire 32 i x_func [31:0] $end
       $var wire 64 j z_sqr [63:0] $end
       $var wire 64 l z_shift [63:0] $end
      $upscope $end
     $upscope $end
     $scope module module_pe_sum2 $end
      $var wire 1 M! clk $end
      $var wire 1 N! rst $end
      $var wire 1 ^! op $end
      $var wire 1 1! e $end
      $var wire 32 I! op1 [31:0] $end
      $var wire 32 K! op2 [31:0] $end
      $var wire 32 J! res [31:0] $end
      $var wire 32 X! DOUBLE_SIZE [31:0] $end
      $var wire 32 Y! SINGLE_SIZE [31:0] $end
      $var wire 1 n e_ff $end
      $var wire 64 o op1_ff [63:0] $end
      $var wire 64 q op2_ff [63:0] $end
      $var wire 64 T! res_ff [63:0] $end
      $var wire 32 s sigm [31:0] $end
      $var wire 32 t x [31:0] $end
      $scope module sigmoid_i $end
       $var wire 32 t x [31:0] $end
       $var wire 32 s y [31:0] $end
       $var wire 32 Z! MT4 [31:0] $end
       $var wire 32 X! DOUBLE_SIZE [31:0] $end
       $var wire 32 Y! SINGLE_SIZE [31:0] $end
       $var wire 32 [! HALF_SIZE [31:0] $end
       $var wire 32 \! HALF [31:0] $end
       $var wire 32 ]! HALF_NEG [31:0] $end
       $var wire 1 u neg $end
       $var wire 1 v more_then_4 $end
       $var wire 64 w z [63:0] $end
       $var wire 64 y x_signed [63:0] $end
       $var wire 32 { x_func [31:0] $end
       $var wire 64 | z_sqr [63:0] $end
       $var wire 64 ~ z_shift [63:0] $end
      $upscope $end
     $upscope $end
     $scope module storage_queue_i1 $end
      $var wire 1 M! clk $end
      $var wire 1 N! rst $end
      $var wire 1 9! push $end
      $var wire 1 =! pop $end
      $var wire 1 A! reset $end
      $var wire 1 C! next $end
      $var wire 32 L! data_in [31:0] $end
      $var wire 32 G! data_out [31:0] $end
      $var wire 1 0 empty $end
      $var wire 6 "! addr_start [5:0] $end
      $var wire 6 #! addr_end [5:0] $end
      $var wire 6 $! addr_end_tmp [5:0] $end
      $var wire 6 (! addr_start_next [5:0] $end
      $var wire 6 )! addr_end_next [5:0] $end
      $var wire 6 *! addr_end_tmp_next [5:0] $end
     $upscope $end
     $scope module storage_queue_i2 $end
      $var wire 1 M! clk $end
      $var wire 1 N! rst $end
      $var wire 1 :! push $end
      $var wire 1 >! pop $end
      $var wire 1 B! reset $end
      $var wire 1 D! next $end
      $var wire 32 L! data_in [31:0] $end
      $var wire 32 H! data_out [31:0] $end
      $var wire 1 1 empty $end
      $var wire 6 %! addr_start [5:0] $end
      $var wire 6 &! addr_end [5:0] $end
      $var wire 6 '! addr_end_tmp [5:0] $end
      $var wire 6 +! addr_start_next [5:0] $end
      $var wire 6 ,! addr_end_next [5:0] $end
      $var wire 6 -! addr_end_tmp_next [5:0] $end
     $upscope $end
    $upscope $end
   $upscope $end
   $scope module mem_i $end
    $var wire 1 M! clk $end
    $var wire 1 # rd $end
    $var wire 1 $ wr $end
    $var wire 11 % addr [10:0] $end
    $var wire 40 & data_in [39:0] $end
    $var wire 40 .! data_out [39:0] $end
   $upscope $end
   $scope module unnamedblk1 $end
    $var wire 32 - i [31:0] $end
   $upscope $end
   $scope module unnamedblk2 $end
    $var wire 32 . i [31:0] $end
   $upscope $end
  $upscope $end
 $upscope $end
$enddefinitions $end


#0
0#
0$
b00000000000 %
b0000000000000000000000000000000000000000 &
b10000000000000000000000000101100 (
b00000000 )
b0000000000000000000000000000000000000000 *
b00000000000000000000000000000000 ,
b00000000000000000000000000000000 -
b00000000000000000000000000000000 .
1/
10
11
b00000000000000000000000000000000 2
b00000000000000000000000000000000 3
04
b0000000000000000000000000000000000000000000000000000000000000000 5
b0000000000000000000000000000000000000000000000000000000000000000 7
b0000000000000000000000000000000000000000000000000000000000000000 9
b11111111111111111111111111111111 ;
b00000000000000000000000000000000 <
0=
0>
b1111111111111111111111111111111111111111111111110000000000000000 ?
b0000000000000000000000000000000000000000000000000000000000000000 A
b11111111111111110000000000000000 C
b0000000000000000000000000000000100000000000000000000000000000000 D
b0000000000000000000000000000000000000000000000001000000000000000 F
0H
b0000000000000000000000000000000000000000000000000000000000000000 I
b0000000000000000000000000000000000000000000000000000000000000000 K
b0000000000000000000000000000000000000000000000000000000000000000 M
b11111111111111111111111111111111 O
b00000000000000000000000000000000 P
0Q
0R
b1111111111111111111111111111111111111111111111110000000000000000 S
b0000000000000000000000000000000000000000000000000000000000000000 U
b11111111111111110000000000000000 W
b0000000000000000000000000000000100000000000000000000000000000000 X
b0000000000000000000000000000000000000000000000001000000000000000 Z
0\
b0000000000000000000000000000000000000000000000000000000000000000 ]
b0000000000000000000000000000000000000000000000000000000000000000 _
b11111111111111111111111111111111 a
b00000000000000000000000000000000 b
0c
0d
b1111111111111111111111111111111111111111111111110000000000000000 e
b0000000000000000000000000000000000000000000000000000000000000000 g
b11111111111111110000000000000000 i
b0000000000000000000000000000000100000000000000000000000000000000 j
b0000000000000000000000000000000000000000000000001000000000000000 l
0n
b0000000000000000000000000000000000000000000000000000000000000000 o
b0000000000000000000000000000000000000000000000000000000000000000 q
b11111111111111111111111111111111 s
b00000000000000000000000000000000 t
0u
0v
b1111111111111111111111111111111111111111111111110000000000000000 w
b0000000000000000000000000000000000000000000000000000000000000000 y
b11111111111111110000000000000000 {
b0000000000000000000000000000000100000000000000000000000000000000 |
b0000000000000000000000000000000000000000000000001000000000000000 ~
b000000 "!
b000000 #!
b000000 $!
b000000 %!
b000000 &!
b000000 '!
b000000 (!
b000000 )!
b000000 *!
b000000 +!
b000000 ,!
b000000 -!
b0000000000000000000000000000000000000000 .!
00!
01!
02!
03!
04!
05!
06!
07!
b00000000000000000000000000000000 8!
09!
0:!
0;!
0<!
0=!
0>!
0?!
0@!
0A!
0B!
0C!
0D!
b00000000000000000000000000000000 E!
b00000000000000000000000000000000 F!
b00000000000000000000000000000000 G!
b00000000000000000000000000000000 H!
b00000000000000000000000000000000 I!
b00000000000000000000000000000000 J!
b00000000000000000000000000000000 K!
b00000000000000000000000000000000 L!
0M!
1N!
b00000000000000000000000000000000 O!
r0 P!
b0000000000000000000000000000000000000000000000000000000000000000 R!
b0000000000000000000000000000000000000000000000000000000000000000 T!
b00000000000000000000000000000101 V!
1W!
b00000000000000000000000001000000 X!
b00000000000000000000000000100000 Y!
b00000000000000000000000000010010 Z!
b00000000000000000000000000010000 [!
b00000000000000001000000000000000 \!
b11111111111111110111111111111111 ]!
0^!
#5
1$
b0010000000000000000000000000000000000000 &
b0010000000000000000000000000000000000000 *
b00000000000000000000000000000001 ,
b00000000000000000000000000000101 -
1M!
b00000000000000000000000000000001 O!
r32769 P!
#10
0M!
0N!
#15
b00000000001 %
b0001000000000000000000000000000000000000 &
b0001000000000000000000000000000000000000 *
b00000000000000000000000000000010 ,
1M!
b00000000000000000000000000000010 O!
#20
0M!
#25
b00000000010 %
b0010000000000000000000000000000000000000 &
b0010000000000000000000000000000000000000 *
b00000000000000000000000000000011 ,
1M!
b00000000000000000000000000000011 O!
#30
0M!
#35
b00000000011 %
b0001000000000000000000000000000000000000 &
b0001000000000000000000000000000000000000 *
b00000000000000000000000000000100 ,
1M!
b00000000000000000000000000000100 O!
#40
0M!
#45
b00000000100 %
b0010000000000000000000000000000000000000 &
b0010000000000000000000000000000000000000 *
b00000000000000000000000000000101 ,
1M!
b00000000000000000000000000000101 O!
#50
0M!
#55
b00000000101 %
b0001000000000000000000000000000000000000 &
b0001000000000000000000000000000000000000 *
b00000000000000000000000000000110 ,
1M!
b00000000000000000000000000000110 O!
#60
0M!
#65
b00000000110 %
b0010000000000000000000000000000000000000 &
b0010000000000000000000000000000000000000 *
b00000000000000000000000000000111 ,
1M!
b00000000000000000000000000000111 O!
#70
0M!
#75
b00000000111 %
b0001000000000000000000000000000000000000 &
b0001000000000000000000000000000000000000 *
b00000000000000000000000000001000 ,
1M!
b00000000000000000000000000001000 O!
#80
0M!
#85
b00000001000 %
b0010000000000000000000010000000000000000 &
b0010000000000000000000010000000000000000 *
b00000000000000000000000000001001 ,
1M!
b00000000000000000000000000001001 O!
#90
0M!
#95
b00000001001 %
b0001000000000000000000010000000000000000 &
b0001000000000000000000010000000000000000 *
b00000000000000000000000000001010 ,
1M!
b00000000000000000000000000001010 O!
#100
0M!
#105
b00000001010 %
b0010000000000000000000010000000000000000 &
b0010000000000000000000010000000000000000 *
b00000000000000000000000000001011 ,
1M!
b00000000000000000000000000001011 O!
#110
0M!
#115
b00000001011 %
b0001000000000000000000010000000000000000 &
b0001000000000000000000010000000000000000 *
b00000000000000000000000000001100 ,
1M!
b00000000000000000000000000001100 O!
#120
0M!
#125
b00000001100 %
b0010000000000000000000010000000000000000 &
b0010000000000000000000010000000000000000 *
b00000000000000000000000000001101 ,
1M!
b00000000000000000000000000001101 O!
#130
0M!
#135
b00000001101 %
b0001000000000000000000000000000000000000 &
b0001000000000000000000000000000000000000 *
b00000000000000000000000000001110 ,
1M!
b00000000000000000000000000001110 O!
#140
0M!
#145
b00000001110 %
b0010000000000000000000000000000000000000 &
b0010000000000000000000000000000000000000 *
b00000000000000000000000000001111 ,
1M!
b00000000000000000000000000001111 O!
#150
0M!
#155
b00000001111 %
b0001000000000000000000010000000000000000 &
b0001000000000000000000010000000000000000 *
b00000000000000000000000000010000 ,
1M!
b00000000000000000000000000010000 O!
#160
0M!
#165
b00000010000 %
b0010000000000000000000000000000000000000 &
b0010000000000000000000000000000000000000 *
b00000000000000000000000000010001 ,
1M!
b00000000000000000000000000010001 O!
#170
0M!
#175
b00000010001 %
b0001000000000000000000000000000000000000 &
b0001000000000000000000000000000000000000 *
b00000000000000000000000000010010 ,
1M!
b00000000000000000000000000010010 O!
#180
0M!
#185
b00000010010 %
b0010000000000000000000000000000000000000 &
b0010000000000000000000000000000000000000 *
b00000000000000000000000000010011 ,
1M!
b00000000000000000000000000010011 O!
#190
0M!
#195
b00000010011 %
b0001000000000000000000010000000000000000 &
b0001000000000000000000010000000000000000 *
b00000000000000000000000000010100 ,
1M!
b00000000000000000000000000010100 O!
#200
0M!
#205
b00000010100 %
b0010000000000000000000000000000000000000 &
b0010000000000000000000000000000000000000 *
b00000000000000000000000000010101 ,
1M!
b00000000000000000000000000010101 O!
#210
0M!
#215
b00000010101 %
b0001000000000000000000000000000000000000 &
b0001000000000000000000000000000000000000 *
b00000000000000000000000000010110 ,
1M!
b00000000000000000000000000010110 O!
#220
0M!
#225
b00000010110 %
b0010000000000000000000010000000000000000 &
b0010000000000000000000010000000000000000 *
b00000000000000000000000000010111 ,
1M!
b00000000000000000000000000010111 O!
#230
0M!
#235
b00000010111 %
b0001000000000000000000000000000000000000 &
b0001000000000000000000000000000000000000 *
b00000000000000000000000000011000 ,
1M!
b00000000000000000000000000011000 O!
#240
0M!
#245
b00000011000 %
b0010000000000000000000000000000000000000 &
b0010000000000000000000000000000000000000 *
b00000000000000000000000000011001 ,
1M!
b00000000000000000000000000011001 O!
#250
0M!
#255
b00000011001 %
b0001000000000000000000000000000000000000 &
b0001000000000000000000000000000000000000 *
b00000000000000000000000000011010 ,
1M!
b00000000000000000000000000011010 O!
#260
0M!
#265
b00000011010 %
b0010000000000000000000010000000000000000 &
b0010000000000000000000010000000000000000 *
b00000000000000000000000000011011 ,
1M!
b00000000000000000000000000011011 O!
#270
0M!
